AUTHORS
CHANGES
COPYING
INSTALL
MANIFEST.in
README
setup.cfg
setup.py
bin/quant-admin
bin/quant-makeconfig
bin/quant-test
bin/quantvirtualenvhandlers.py
doc/quant-domain-analysis.txt
doc/quant-dsl-definition-and-proof.bbl
doc/quant-dsl-definition-and-proof.bib
doc/quant-dsl-definition-and-proof.pdf
doc/quant-dsl-definition-and-proof.tex
src/quant/__init__.py
src/quant/accesscontrol.py
src/quant/builder.py
src/quant/dependencygraph.py
src/quant/dependencygraphtest.py
src/quant/dictionary.py
src/quant/dictionarywords.py
src/quant/dippy.py
src/quant/dippy_example.py
src/quant/djangotest.py
src/quant/domtest.py
src/quant/exceptions.py
src/quant/filesystem.py
src/quant/googlefinance.py
src/quant/leastsquares.py
src/quant/leastsquarestest.py
src/quant/market.py
src/quant/markettest.py
src/quant/plugintest.py
src/quant/regexps.py
src/quant/soleInstance.py
src/quant/stats.py
src/quant/statstest.py
src/quant/test.py
src/quant/testunit.py
src/quant/url.py
src/quant.egg-info/PKG-INFO
src/quant.egg-info/SOURCES.txt
src/quant.egg-info/dependency_links.txt
src/quant.egg-info/not-zip-safe
src/quant.egg-info/requires.txt
src/quant.egg-info/top_level.txt
src/quant/application/__init__.py
src/quant/cli/__init__.py
src/quant/cli/admin.py
src/quant/command/__init__.py
src/quant/command/initialise.py
src/quant/command/initialisetest.py
src/quant/contracttype/__init__.py
src/quant/contracttype/simple.py
src/quant/contracttype/simpletest.py
src/quant/contracttype/test.py
src/quant/djangoapp/__init__.py
src/quant/djangoapp/settingstest.py
src/quant/djangoapp/apps/__init__.py
src/quant/djangoapp/apps/eui/__init__.py
src/quant/djangoapp/apps/eui/views/__init__.py
src/quant/djangoapp/apps/eui/views/accesscontrol.py
src/quant/djangoapp/apps/eui/views/admin.py
src/quant/djangoapp/apps/eui/views/api.py
src/quant/djangoapp/apps/eui/views/apitest.py
src/quant/djangoapp/apps/eui/views/base.py
src/quant/djangoapp/apps/eui/views/calculator.py
src/quant/djangoapp/apps/eui/views/manipulator.py
src/quant/djangoapp/apps/eui/views/person.py
src/quant/djangoapp/apps/eui/views/registry.py
src/quant/djangoapp/apps/eui/views/test.py
src/quant/djangoapp/apps/eui/views/testbase.py
